dtmaster_ingest_douglasleal/__init__.py
dtmaster_ingest_douglasleal/input.py
dtmaster_ingest_douglasleal-0.1.1.dist-info/LICENSE
dtmaster_ingest_douglasleal-0.1.1.dist-info/METADATA
dtmaster_ingest_douglasleal-0.1.1.dist-info/WHEEL
dtmaster_ingest_douglasleal-0.1.1.dist-info/RECORD
